{
  "name": "NumberInput",
  "type": "component",
  "filePath": "src/components/ui/NumberInput.astro",
  "description": "NumberInput Component",
  "props": {
    "value": {
      "type": "number",
      "optional": true,
      "default": 0
    },
    "min": {
      "type": "number",
      "optional": true,
      "default": ""
    },
    "max": {
      "type": "number",
      "optional": true,
      "default": ""
    },
    "step": {
      "type": "number",
      "optional": true,
      "default": 1
    },
    "name": {
      "type": "string",
      "optional": true,
      "default": ""
    },
    "id": {
      "type": "string",
      "optional": true,
      "default": ""
    },
    "disabled": {
      "type": "boolean",
      "optional": true,
      "default": false
    },
    "label": {
      "type": "string",
      "optional": true,
      "default": ""
    },
    "labelVariant": {
      "type": "'inline' | 'stacked'",
      "optional": true,
      "default": ""
    },
    "labelFor": {
      "type": "string",
      "optional": true,
      "default": ""
    },
    "class": {
      "type": "string",
      "optional": true,
      "default": ""
    }
  },
  "imports": {
    "Icon": "./Icon.astro",
    "Label": "./Label.astro"
  },
  "dependencies": [
    "Icon",
    "Label"
  ],
  "cssClasses": [
    "number-input-form-wrapper",
    "number-input-form-wrapper--inline",
    "number-input-form-wrapper--stacked",
    "number-input-form-wrapper__label",
    "number-input",
    "number-input__btn",
    "number-input__input"
  ],
  "themeSupport": {
    "themes": [
      "cp",
      "vp",
      "ppm",
      "maconomy"
    ],
    "darkMode": true
  },
  "slots": {},
  "structure": {
    "root": {
      "element": "div",
      "class": "number-input-form-wrapper",
      "spacing": {
        "padding": "0",
        "margin": "0"
      },
      "baseClass": "number-input-form-wrapper",
      "modifierClasses": {
        "inline": "number-input-form-wrapper--inline",
        "stacked": "number-input-form-wrapper--stacked"
      },
      "children": [
        {
          "element": "Label",
          "class": "number-input-form-wrapper__label",
          "spacing": {
            "padding": "0",
            "margin": "0"
          },
          "children": []
        },
        {
          "element": "div",
          "class": "number-input",
          "spacing": {
            "padding": "0",
            "margin": "0"
          },
          "children": [
            {
              "element": "button",
              "class": "number-input__btn",
              "spacing": {
                "padding": "0",
                "margin": "0"
              },
              "children": [
                {
                  "element": "Icon",
                  "class": "",
                  "spacing": {
                    "padding": "0",
                    "margin": "0"
                  },
                  "children": []
                }
              ]
            },
            {
              "element": "input",
              "class": "number-input__input",
              "spacing": {
                "padding": "0",
                "margin": "0"
              },
              "children": []
            },
            {
              "element": "button",
              "class": "number-input__btn",
              "spacing": {
                "padding": "0",
                "margin": "0"
              },
              "children": [
                {
                  "element": "Icon",
                  "class": "",
                  "spacing": {
                    "padding": "0",
                    "margin": "0"
                  },
                  "children": []
                }
              ]
            }
          ]
        }
      ]
    },
    "children": [
      {
        "element": "script",
        "class": "",
        "spacing": {
          "padding": "0",
          "margin": "0"
        },
        "children": []
      }
    ]
  },
  "_metadata": {
    "lastGenerated": "2026-01-23T01:33:50.768Z",
    "generatedWith": "@astrojs/compiler@2.13.0",
    "includesVisualSpecs": true,
    "availableVariants": [
      "inline",
      "stacked"
    ]
  },
  "visualSpecifications": {
    "dimensions": {
      "xs": {
        "height": "40px",
        "width": "auto",
        "minWidth": "auto",
        "maxWidth": "none"
      },
      "sm": {
        "height": "40px",
        "width": "auto",
        "minWidth": "auto",
        "maxWidth": "none"
      },
      "md": {
        "height": "40px",
        "width": "auto",
        "minWidth": "auto",
        "maxWidth": "none"
      },
      "lg": {
        "height": "40px",
        "width": "auto",
        "minWidth": "auto",
        "maxWidth": "none"
      }
    },
    "spacing": {
      "xs": {
        "paddingTop": "0",
        "paddingRight": "0",
        "paddingBottom": "0",
        "paddingLeft": "0",
        "gap": "0"
      },
      "sm": {
        "paddingTop": "0",
        "paddingRight": "0",
        "paddingBottom": "0",
        "paddingLeft": "0",
        "gap": "0"
      },
      "md": {
        "paddingTop": "0",
        "paddingRight": "0",
        "paddingBottom": "0",
        "paddingLeft": "0",
        "gap": "0"
      },
      "lg": {
        "paddingTop": "0",
        "paddingRight": "0",
        "paddingBottom": "0",
        "paddingLeft": "0",
        "gap": "0"
      }
    },
    "typography": {
      "fontFamily": "'Figtree', sans-serif",
      "fontWeight": "400",
      "lineHeight": "1.5",
      "letterSpacing": "0",
      "textTransform": "none",
      "sizes": {
        "xs": {
          "fontSize": "0.75rem",
          "lineHeight": "1.5"
        },
        "sm": {
          "fontSize": "0.75rem",
          "lineHeight": "1.5"
        },
        "md": {
          "fontSize": "1rem",
          "lineHeight": "1.5"
        },
        "lg": {
          "fontSize": "1rem",
          "lineHeight": "1.5"
        }
      }
    },
    "borders": {
      "width": "1px",
      "style": "solid",
      "radius": {
        "default": "0.5rem",
        "cp": "0.5rem"
      }
    },
    "colors": {
      "variants": {
        "default": {
          "cp": {
            "light": {
              "default": {
                "container": {
                  "background": "transparent",
                  "border": "#BFC6D4",
                  "borderRadius": "0.5rem"
                },
                "button": {
                  "background": "#F7F8FA",
                  "text": "#525969",
                  "border": "transparent",
                  "iconColor": "#525969",
                  "width": "40px",
                  "minWidth": "44px",
                  "minHeight": "44px"
                },
                "input": {
                  "background": "#FFFFFF",
                  "text": "#373F4E",
                  "border": "none",
                  "borderLeft": "1px solid #BFC6D4",
                  "borderRight": "1px solid #BFC6D4",
                  "width": "60px",
                  "height": "40px",
                  "minHeight": "44px",
                  "fontSize": "1rem"
                }
              },
              "hover": {
                "button": {
                  "background": "#E5E7EB",
                  "text": "#373F4E",
                  "iconColor": "#373F4E"
                }
              },
              "focus": {
                "container": {
                  "border": "#4C92D9",
                  "boxShadow": "0 0 0 3px rgba(76, 146, 217, 0.1), 0 0 0 4px #F7F8FA"
                },
                "input": {
                  "outline": "none"
                }
              },
              "disabled": {
                "button": {
                  "text": "#6B7280",
                  "iconColor": "#6B7280",
                  "cursor": "not-allowed"
                },
                "input": {
                  "background": "#EAEAEA",
                  "cursor": "not-allowed"
                }
              }
            },
            "dark": {
              "default": {
                "container": {
                  "background": "transparent",
                  "border": "#5F6871",
                  "borderRadius": "0.5rem"
                },
                "button": {
                  "background": "#37424D",
                  "text": "#B6B6C4",
                  "border": "transparent",
                  "iconColor": "#B6B6C4",
                  "width": "40px",
                  "minWidth": "44px",
                  "minHeight": "44px"
                },
                "input": {
                  "background": "#1F252E",
                  "text": "#E9ECEF",
                  "border": "none",
                  "borderLeft": "1px solid #5F6871",
                  "borderRight": "1px solid #5F6871",
                  "width": "60px",
                  "height": "40px",
                  "minHeight": "44px",
                  "fontSize": "1rem"
                }
              },
              "hover": {
                "button": {
                  "background": "#3D4A5C",
                  "text": "#E9ECEF",
                  "iconColor": "#E9ECEF"
                }
              },
              "focus": {
                "container": {
                  "border": "#59ACFF",
                  "boxShadow": "0 0 0 3px rgba(89, 172, 255, 0.1), 0 0 0 4px #37424D"
                },
                "input": {
                  "outline": "none"
                }
              },
              "disabled": {
                "button": {
                  "text": "#BBBBC6",
                  "iconColor": "#BBBBC6",
                  "cursor": "not-allowed"
                },
                "input": {
                  "background": "#333D47",
                  "cursor": "not-allowed"
                }
              }
            }
          },
          "vp": {
            "light": {
              "default": {
                "container": {
                  "background": "transparent",
                  "border": "#BFC6D4",
                  "borderRadius": "0.5rem"
                },
                "button": {
                  "background": "#F7F8FA",
                  "text": "#525969",
                  "border": "transparent",
                  "iconColor": "#525969",
                  "width": "40px",
                  "minWidth": "44px",
                  "minHeight": "44px"
                },
                "input": {
                  "background": "#FFFFFF",
                  "text": "#373F4E",
                  "border": "none",
                  "borderLeft": "1px solid #BFC6D4",
                  "borderRight": "1px solid #BFC6D4",
                  "width": "60px",
                  "height": "40px",
                  "minHeight": "44px",
                  "fontSize": "1rem"
                }
              },
              "hover": {
                "button": {
                  "background": "#E5E7EB",
                  "text": "#373F4E",
                  "iconColor": "#373F4E"
                }
              },
              "focus": {
                "container": {
                  "border": "#4C92D9",
                  "boxShadow": "0 0 0 3px rgba(76, 146, 217, 0.1), 0 0 0 4px #F7F8FA"
                },
                "input": {
                  "outline": "none"
                }
              },
              "disabled": {
                "button": {
                  "text": "#6B7280",
                  "iconColor": "#6B7280",
                  "cursor": "not-allowed"
                },
                "input": {
                  "background": "#EAEAEA",
                  "cursor": "not-allowed"
                }
              }
            },
            "dark": {
              "default": {
                "container": {
                  "background": "transparent",
                  "border": "#2A2D32",
                  "borderRadius": "0.5rem"
                },
                "button": {
                  "background": "#1F2124",
                  "text": "#B5B5BC",
                  "border": "transparent",
                  "iconColor": "#B5B5BC",
                  "width": "40px",
                  "minWidth": "44px",
                  "minHeight": "44px"
                },
                "input": {
                  "background": "#1F2124",
                  "text": "#FAFAFA",
                  "border": "none",
                  "borderLeft": "1px solid #2A2D32",
                  "borderRight": "1px solid #2A2D32",
                  "width": "60px",
                  "height": "40px",
                  "minHeight": "44px",
                  "fontSize": "1rem"
                }
              },
              "hover": {
                "button": {
                  "background": "#2A2D32",
                  "text": "#FAFAFA",
                  "iconColor": "#FAFAFA"
                }
              },
              "focus": {
                "container": {
                  "border": "#59ACFF",
                  "boxShadow": "0 0 0 3px rgba(89, 172, 255, 0.1), 0 0 0 4px #1F2124"
                },
                "input": {
                  "outline": "none"
                }
              },
              "disabled": {
                "button": {
                  "text": "#B5B5BC",
                  "iconColor": "#B5B5BC",
                  "cursor": "not-allowed"
                },
                "input": {
                  "background": "#2A2D32",
                  "cursor": "not-allowed"
                }
              }
            }
          },
          "ppm": {
            "light": {
              "default": {
                "container": {
                  "background": "transparent",
                  "border": "#BFC6D4",
                  "borderRadius": "0.5rem"
                },
                "button": {
                  "background": "#F7F8FA",
                  "text": "#525969",
                  "border": "transparent",
                  "iconColor": "#525969",
                  "width": "40px",
                  "minWidth": "44px",
                  "minHeight": "44px"
                },
                "input": {
                  "background": "#FFFFFF",
                  "text": "#373F4E",
                  "border": "none",
                  "borderLeft": "1px solid #BFC6D4",
                  "borderRight": "1px solid #BFC6D4",
                  "width": "60px",
                  "height": "40px",
                  "minHeight": "44px",
                  "fontSize": "1rem"
                }
              },
              "hover": {
                "button": {
                  "background": "#E5E7EB",
                  "text": "#373F4E",
                  "iconColor": "#373F4E"
                }
              },
              "focus": {
                "container": {
                  "border": "#4C92D9",
                  "boxShadow": "0 0 0 3px rgba(76, 146, 217, 0.1), 0 0 0 4px #F7F8FA"
                },
                "input": {
                  "outline": "none"
                }
              },
              "disabled": {
                "button": {
                  "text": "#6B7280",
                  "iconColor": "#6B7280",
                  "cursor": "not-allowed"
                },
                "input": {
                  "background": "#EAEAEA",
                  "cursor": "not-allowed"
                }
              }
            },
            "dark": {
              "default": {
                "container": {
                  "background": "transparent",
                  "border": "#2A2D32",
                  "borderRadius": "0.5rem"
                },
                "button": {
                  "background": "#1F2124",
                  "text": "#B5B5BC",
                  "border": "transparent",
                  "iconColor": "#B5B5BC",
                  "width": "40px",
                  "minWidth": "44px",
                  "minHeight": "44px"
                },
                "input": {
                  "background": "#1F2124",
                  "text": "#FAFAFA",
                  "border": "none",
                  "borderLeft": "1px solid #2A2D32",
                  "borderRight": "1px solid #2A2D32",
                  "width": "60px",
                  "height": "40px",
                  "minHeight": "44px",
                  "fontSize": "1rem"
                }
              },
              "hover": {
                "button": {
                  "background": "#2A2D32",
                  "text": "#FAFAFA",
                  "iconColor": "#FAFAFA"
                }
              },
              "focus": {
                "container": {
                  "border": "#59ACFF",
                  "boxShadow": "0 0 0 3px rgba(89, 172, 255, 0.1), 0 0 0 4px #1F2124"
                },
                "input": {
                  "outline": "none"
                }
              },
              "disabled": {
                "button": {
                  "text": "#B5B5BC",
                  "iconColor": "#B5B5BC",
                  "cursor": "not-allowed"
                },
                "input": {
                  "background": "#2A2D32",
                  "cursor": "not-allowed"
                }
              }
            }
          },
          "maconomy": {
            "light": {
              "default": {
                "container": {
                  "background": "transparent",
                  "border": "#BFC6D4",
                  "borderRadius": "0.5rem"
                },
                "button": {
                  "background": "#F7F8FA",
                  "text": "#525969",
                  "border": "transparent",
                  "iconColor": "#525969",
                  "width": "40px",
                  "minWidth": "44px",
                  "minHeight": "44px"
                },
                "input": {
                  "background": "#FFFFFF",
                  "text": "#373F4E",
                  "border": "none",
                  "borderLeft": "1px solid #BFC6D4",
                  "borderRight": "1px solid #BFC6D4",
                  "width": "60px",
                  "height": "40px",
                  "minHeight": "44px",
                  "fontSize": "1rem"
                }
              },
              "hover": {
                "button": {
                  "background": "#E5E7EB",
                  "text": "#373F4E",
                  "iconColor": "#373F4E"
                }
              },
              "focus": {
                "container": {
                  "border": "#4C92D9",
                  "boxShadow": "0 0 0 3px rgba(76, 146, 217, 0.1), 0 0 0 4px #F7F8FA"
                },
                "input": {
                  "outline": "none"
                }
              },
              "disabled": {
                "button": {
                  "text": "#6B7280",
                  "iconColor": "#6B7280",
                  "cursor": "not-allowed"
                },
                "input": {
                  "background": "#EAEAEA",
                  "cursor": "not-allowed"
                }
              }
            },
            "dark": {
              "default": {
                "container": {
                  "background": "transparent",
                  "border": "#2A2D32",
                  "borderRadius": "0.5rem"
                },
                "button": {
                  "background": "#1F2124",
                  "text": "#B5B5BC",
                  "border": "transparent",
                  "iconColor": "#B5B5BC",
                  "width": "40px",
                  "minWidth": "44px",
                  "minHeight": "44px"
                },
                "input": {
                  "background": "#1F2124",
                  "text": "#FAFAFA",
                  "border": "none",
                  "borderLeft": "1px solid #2A2D32",
                  "borderRight": "1px solid #2A2D32",
                  "width": "60px",
                  "height": "40px",
                  "minHeight": "44px",
                  "fontSize": "1rem"
                }
              },
              "hover": {
                "button": {
                  "background": "#2A2D32",
                  "text": "#FAFAFA",
                  "iconColor": "#FAFAFA"
                }
              },
              "focus": {
                "container": {
                  "border": "#59ACFF",
                  "boxShadow": "0 0 0 3px rgba(89, 172, 255, 0.1), 0 0 0 4px #1F2124"
                },
                "input": {
                  "outline": "none"
                }
              },
              "disabled": {
                "button": {
                  "text": "#B5B5BC",
                  "iconColor": "#B5B5BC",
                  "cursor": "not-allowed"
                },
                "input": {
                  "background": "#2A2D32",
                  "cursor": "not-allowed"
                }
              }
            }
          }
        }
      }
    },
    "elevation": {
      "default": "none",
      "hover": "none",
      "active": "none",
      "focus": {
        "cp": {
          "light": "0 0 0 3px rgba(76, 146, 217, 0.1), 0 0 0 4px #F7F8FA",
          "dark": "0 0 0 3px rgba(89, 172, 255, 0.1), 0 0 0 4px #37424D"
        },
        "vp": {
          "light": "0 0 0 3px rgba(76, 146, 217, 0.1), 0 0 0 4px #F7F8FA",
          "dark": "0 0 0 3px rgba(89, 172, 255, 0.1), 0 0 0 4px #1F2124"
        },
        "ppm": {
          "light": "0 0 0 3px rgba(76, 146, 217, 0.1), 0 0 0 4px #F7F8FA",
          "dark": "0 0 0 3px rgba(89, 172, 255, 0.1), 0 0 0 4px #1F2124"
        },
        "maconomy": {
          "light": "0 0 0 3px rgba(76, 146, 217, 0.1), 0 0 0 4px #F7F8FA",
          "dark": "0 0 0 3px rgba(89, 172, 255, 0.1), 0 0 0 4px #1F2124"
        }
      }
    },
    "transitions": {
      "default": "all 150ms ease",
      "properties": {
        "background-color": "background-color 150ms ease",
        "color": "color 150ms ease",
        "border-color": "border-color 150ms ease",
        "box-shadow": "box-shadow 150ms ease"
      }
    },
    "layout": {
      "display": "inline-flex",
      "alignItems": "stretch",
      "justifyContent": "flex-start",
      "flexDirection": "row"
    },
    "iconSpecs": {
      "decrement": {
        "name": "minus",
        "size": "md",
        "width": "20px",
        "height": "20px",
        "variant": "outline",
        "strokeWidth": "1.5",
        "color": "currentColor"
      },
      "increment": {
        "name": "plus",
        "size": "md",
        "width": "20px",
        "height": "20px",
        "variant": "outline",
        "strokeWidth": "1.5",
        "color": "currentColor"
      },
      "states": {
        "default": {
          "cp": {
            "light": {
              "iconColor": "#525969"
            },
            "dark": {
              "iconColor": "#B6B6C4"
            }
          },
          "vp": {
            "light": {
              "iconColor": "#525969"
            },
            "dark": {
              "iconColor": "#B5B5BC"
            }
          },
          "ppm": {
            "light": {
              "iconColor": "#525969"
            },
            "dark": {
              "iconColor": "#B5B5BC"
            }
          },
          "maconomy": {
            "light": {
              "iconColor": "#525969"
            },
            "dark": {
              "iconColor": "#B5B5BC"
            }
          }
        },
        "hover": {
          "cp": {
            "light": {
              "iconColor": "#373F4E"
            },
            "dark": {
              "iconColor": "#E9ECEF"
            }
          },
          "vp": {
            "light": {
              "iconColor": "#373F4E"
            },
            "dark": {
              "iconColor": "#FAFAFA"
            }
          },
          "ppm": {
            "light": {
              "iconColor": "#373F4E"
            },
            "dark": {
              "iconColor": "#FAFAFA"
            }
          },
          "maconomy": {
            "light": {
              "iconColor": "#373F4E"
            },
            "dark": {
              "iconColor": "#FAFAFA"
            }
          }
        },
        "disabled": {
          "cp": {
            "light": {
              "iconColor": "#6B7280"
            },
            "dark": {
              "iconColor": "#BBBBC6"
            }
          },
          "vp": {
            "light": {
              "iconColor": "#6B7280"
            },
            "dark": {
              "iconColor": "#B5B5BC"
            }
          },
          "ppm": {
            "light": {
              "iconColor": "#6B7280"
            },
            "dark": {
              "iconColor": "#B5B5BC"
            }
          },
          "maconomy": {
            "light": {
              "iconColor": "#6B7280"
            },
            "dark": {
              "iconColor": "#B5B5BC"
            }
          }
        }
      }
    }
  },
  "accessibility": {
    "role": "",
    "tabIndex": "",
    "keyboardSupport": {
      "arrowUp": "Increment value",
      "arrowDown": "Decrement value",
      "enter": "Submit value",
      "escape": "Cancel editing"
    },
    "ariaAttributes": {
      "button": {
        "aria-label": "Decrease/Increase",
        "aria-disabled": "true when disabled"
      },
      "input": {
        "aria-label": "Number input",
        "aria-valuemin": "min value",
        "aria-valuemax": "max value",
        "aria-valuenow": "current value"
      }
    },
    "focusVisible": {
      "container": "Focus ring on container when input is focused",
      "button": "No focus ring (uses container focus)"
    }
  },
  "cssClassStyles": {
    ".number-input-form-wrapper": {
      "display": "flex",
      "flex-direction": "column"
    },
    ".number-input-form-wrapper--inline": {
      "display": "flex",
      "flex-direction": "row",
      "align-items": "center",
      "gap": "4px"
    },
    ".number-input-form-wrapper--stacked": {
      "display": "flex",
      "flex-direction": "column",
      "gap": "6px"
    },
    ".number-input-form-wrapper__label": {
      "margin-bottom": "0",
      "white-space": "nowrap"
    },
    ".number-input": {
      "display": "inline-flex",
      "align-items": "stretch",
      "border": "1px solid #BFC6D4",
      "border-radius": "0.5rem",
      "overflow": "hidden",
      "transition": "all 150ms ease",
      "width": "100%"
    },
    ".number-input__btn": {
      "width": "40px",
      "display": "flex",
      "align-items": "center",
      "justify-content": "center",
      "background-color": "#F7F8FA",
      "color": "#525969",
      "cursor": "pointer",
      "transition": "all 150ms ease",
      "min-width": "44px",
      "min-height": "44px",
      "border": "none",
      "padding": "0"
    },
    ".number-input__btn:hover": {
      "background-color": "#E5E7EB",
      "color": "#373F4E"
    },
    ".number-input__btn:disabled": {
      "color": "#6B7280",
      "cursor": "not-allowed",
      "opacity": "1"
    },
    ".number-input__input": {
      "width": "60px",
      "height": "40px",
      "text-align": "center",
      "font-family": "'Figtree', sans-serif",
      "font-size": "1rem",
      "color": "#373F4E",
      "background-color": "#FFFFFF",
      "border": "none",
      "border-left": "1px solid #BFC6D4",
      "border-right": "1px solid #BFC6D4",
      "min-height": "44px",
      "padding": "0"
    },
    ".number-input__input:focus": {
      "outline": "none"
    },
    ".number-input:has(.number-input__input:focus)": {
      "border-color": "#4C92D9",
      "box-shadow": "0 0 0 3px rgba(76, 146, 217, 0.1), 0 0 0 4px #F7F8FA"
    },
    ".theme-cp .number-input": {
      "border": "1px solid #BFC6D4"
    },
    ".theme-cp .number-input__input": {
      "height": "20px",
      "width": "40px",
      "font-size": "0.75rem",
      "min-height": "20px"
    },
    ".theme-cp .number-input__btn": {
      "width": "20px",
      "font-size": "0.75rem",
      "min-width": "20px",
      "min-height": "20px"
    },
    ".theme-cp.dark .number-input": {
      "border": "1px solid #5F6871"
    },
    ".theme-cp.dark .number-input__input": {
      "background-color": "#1F252E",
      "color": "#E9ECEF",
      "border-left": "1px solid #5F6871",
      "border-right": "1px solid #5F6871"
    },
    ".theme-cp.dark .number-input__btn": {
      "background-color": "#37424D",
      "color": "#B6B6C4"
    },
    ".theme-cp.dark .number-input__btn:hover": {
      "background-color": "#3D4A5C",
      "color": "#E9ECEF"
    },
    ".theme-cp.dark .number-input__btn:disabled": {
      "color": "#BBBBC6"
    },
    ".theme-cp.dark .number-input:has(.number-input__input:focus)": {
      "border-color": "#59ACFF",
      "box-shadow": "0 0 0 3px rgba(89, 172, 255, 0.1), 0 0 0 4px #37424D"
    },
    ".theme-vp.dark .number-input": {
      "border": "1px solid #2A2D32"
    },
    ".theme-vp.dark .number-input__input": {
      "background-color": "#1F2124",
      "color": "#FAFAFA",
      "border-left": "1px solid #2A2D32",
      "border-right": "1px solid #2A2D32"
    },
    ".theme-vp.dark .number-input__btn": {
      "background-color": "#1F2124",
      "color": "#B5B5BC"
    },
    ".theme-vp.dark .number-input__btn:hover": {
      "background-color": "#2A2D32",
      "color": "#FAFAFA"
    },
    ".theme-vp.dark .number-input:has(.number-input__input:focus)": {
      "border-color": "#59ACFF",
      "box-shadow": "0 0 0 3px rgba(89, 172, 255, 0.1), 0 0 0 4px #1F2124"
    },
    ".theme-ppm.dark .number-input": {
      "border": "1px solid #2A2D32"
    },
    ".theme-ppm.dark .number-input__input": {
      "background-color": "#1F2124",
      "color": "#FAFAFA",
      "border-left": "1px solid #2A2D32",
      "border-right": "1px solid #2A2D32"
    },
    ".theme-ppm.dark .number-input__btn": {
      "background-color": "#1F2124",
      "color": "#B5B5BC"
    },
    ".theme-ppm.dark .number-input__btn:hover": {
      "background-color": "#2A2D32",
      "color": "#FAFAFA"
    },
    ".theme-ppm.dark .number-input:has(.number-input__input:focus)": {
      "border-color": "#59ACFF",
      "box-shadow": "0 0 0 3px rgba(89, 172, 255, 0.1), 0 0 0 4px #1F2124"
    },
    ".theme-maconomy.dark .number-input": {
      "border": "1px solid #2A2D32"
    },
    ".theme-maconomy.dark .number-input__input": {
      "background-color": "#1F2124",
      "color": "#FAFAFA",
      "border-left": "1px solid #2A2D32",
      "border-right": "1px solid #2A2D32"
    },
    ".theme-maconomy.dark .number-input__btn": {
      "background-color": "#1F2124",
      "color": "#B5B5BC"
    },
    ".theme-maconomy.dark .number-input__btn:hover": {
      "background-color": "#2A2D32",
      "color": "#FAFAFA"
    },
    ".theme-maconomy.dark .number-input:has(.number-input__input:focus)": {
      "border-color": "#59ACFF",
      "box-shadow": "0 0 0 3px rgba(89, 172, 255, 0.1), 0 0 0 4px #1F2124"
    }
  },
  "_variantIndex": {},
  "_variantMetadata": {
    "availableVariants": [
      "inline",
      "stacked"
    ]
  },
  "interactivity": {
    "hasInteractivity": true,
    "initialization": {
      "function": "initNumberInputs",
      "triggers": [
        "DOMContentLoaded (implicit via immediate call)",
        "astro:page-load"
      ],
      "preventDoubleInit": true,
      "preventDoubleInitMethod": "data-init attribute on number input container",
      "description": "Initializes all number input components on the page. Sets up increment/decrement button handlers and button state management."
    },
    "state": {
      "inputValue": {
        "type": "number",
        "managedBy": "value attribute on input element",
        "element": ".number-input__input",
        "default": 0,
        "description": "Current numeric value in the input field",
        "updatedBy": "Increment/decrement button clicks, direct input typing, updateButtons function"
      },
      "decrementButtonDisabled": {
        "type": "boolean",
        "managedBy": "disabled attribute on decrement button",
        "element": "[data-number-input-decrement]",
        "description": "Decrement button is disabled when input is disabled OR value is at or below minimum",
        "calculation": "input.disabled || (min !== undefined && value <= min)",
        "updatedBy": "updateButtons function (called on input change and button click)"
      },
      "incrementButtonDisabled": {
        "type": "boolean",
        "managedBy": "disabled attribute on increment button",
        "element": "[data-number-input-increment]",
        "description": "Increment button is disabled when input is disabled OR value is at or above maximum",
        "calculation": "input.disabled || (max !== undefined && value >= max)",
        "updatedBy": "updateButtons function (called on input change and button click)"
      }
    },
    "eventHandlers": [
      {
        "element": "[data-number-input-decrement]",
        "event": "click",
        "handler": "decrementValue",
        "description": "Decrements input value by step amount",
        "condition": "Button is not disabled",
        "actions": [
          "Get current input value (parseFloat(input.value) || 0)",
          "Calculate new value: currentValue - step",
          "Check if new value is >= min (if min is defined)",
          "If valid: Set input.value to new value (as string)",
          "Dispatch 'input' event on input element (bubbles: true)",
          "Call updateButtons() to sync button states"
        ],
        "note": "Only updates value if new value is >= min (when min is defined)"
      },
      {
        "element": "[data-number-input-increment]",
        "event": "click",
        "handler": "incrementValue",
        "description": "Increments input value by step amount",
        "condition": "Button is not disabled",
        "actions": [
          "Get current input value (parseFloat(input.value) || 0)",
          "Calculate new value: currentValue + step",
          "Check if new value is <= max (if max is defined)",
          "If valid: Set input.value to new value (as string)",
          "Dispatch 'input' event on input element (bubbles: true)",
          "Call updateButtons() to sync button states"
        ],
        "note": "Only updates value if new value is <= max (when max is defined)"
      },
      {
        "element": ".number-input__input",
        "event": "input",
        "handler": "updateButtons",
        "description": "Updates button disabled states when input value changes",
        "native": true,
        "actions": [
          "Get current input value (parseFloat(input.value) || 0)",
          "Update decrementBtn.disabled based on: input.disabled || (min !== undefined && val <= min)",
          "Update incrementBtn.disabled based on: input.disabled || (max !== undefined && val >= max)"
        ],
        "note": "Listens to native input event (fired on value change, including direct typing)"
      }
    ],
    "keyboardSupport": {
      "native": {
        "description": "Uses native number input keyboard behavior",
        "ArrowUp": "Increments value by step (native browser behavior)",
        "ArrowDown": "Decrements value by step (native browser behavior)",
        "Tab": "Navigates to next focusable element",
        "Shift+Tab": "Navigates to previous focusable element",
        "Enter": "No special action (native form behavior)",
        "Number keys": "Allow direct value entry (native input behavior)"
      },
      "custom": {
        "description": "Button state management responds to keyboard input changes via input event"
      }
    },
    "dataAttributes": {
      "data-number-input": {
        "purpose": "Identifies number input container element for initialization",
        "required": true,
        "usedBy": "initNumberInputs function to find all number input instances"
      },
      "data-number-input-decrement": {
        "purpose": "Identifies decrement button element",
        "location": "On decrement button",
        "usedBy": "Initialization to find button and attach click handler"
      },
      "data-number-input-increment": {
        "purpose": "Identifies increment button element",
        "location": "On increment button",
        "usedBy": "Initialization to find button and attach click handler"
      },
      "data-init": {
        "purpose": "Prevents double initialization",
        "values": [
          "true"
        ],
        "setBy": "initNumberInputs function after first initialization",
        "checkedBy": "initNumberInputs checks hasAttribute('data-init') before initializing"
      }
    },
    "globalFunctions": {},
    "customEvents": [],
    "dependencies": {
      "internal": [
        "initNumberInputs function",
        "updateButtons function (per-instance)",
        "querySelector/querySelectorAll for element selection"
      ],
      "external": []
    },
    "coordination": {
      "buttonStateManagement": {
        "method": "updateButtons() function called on input change and button click",
        "decrementLogic": "Disabled if input.disabled OR (min defined AND value <= min)",
        "incrementLogic": "Disabled if input.disabled OR (max defined AND value >= max)",
        "description": "Button states automatically sync with input value and min/max constraints"
      },
      "valueConstraints": {
        "min": "Read from input.min attribute (parseFloat), undefined if not set",
        "max": "Read from input.max attribute (parseFloat), undefined if not set",
        "step": "Read from input.step attribute (parseFloat), defaults to 1 if not set",
        "description": "Constraints are read from native input attributes and enforced in button handlers"
      },
      "eventPropagation": {
        "inputEvent": "Dispatched after value change (bubbles: true)",
        "purpose": "Allows parent components to listen for value changes",
        "description": "Native 'input' event is dispatched to maintain compatibility with form libraries"
      },
      "formSubmission": {
        "method": "Native number input participates in form submission",
        "name": "Uses name prop for form field name",
        "value": "Current numeric value submitted with form",
        "description": "Component uses native input element for form integration"
      }
    },
    "implementationNotes": [
      "Initialization runs immediately on script load AND on astro:page-load for SPA navigation",
      "Double initialization prevented by checking data-init attribute before setting up handlers",
      "Step, min, and max values are read from input element attributes (not props) during initialization",
      "Step defaults to 1 if not specified in input.step attribute",
      "Min and max are undefined if not specified (allows unlimited range)",
      "Button disabled states are calculated dynamically based on current value and constraints",
      "updateButtons() is called after every value change (button click or direct input)",
      "Value parsing uses parseFloat() with fallback to 0 if value is empty/invalid",
      "New values are converted to string before setting input.value",
      "Input event is dispatched manually after programmatic value changes to trigger form validation",
      "Button handlers check constraints before updating value (prevents invalid values)",
      "If constraint would be violated, value is not updated and buttons remain in current state",
      "Direct keyboard input (typing numbers) triggers input event, which updates button states",
      "Native browser arrow key increment/decrement also triggers input event",
      "Buttons are disabled in initial render if value is at min/max (checked via disabled prop calculation)",
      "Component supports both controlled (value prop) and uncontrolled (no value prop) usage",
      "All value calculations use parseFloat to handle decimal step values correctly"
    ]
  },
  "iconPaths": {
    "controlIcons": {
      "decrement": {
        "name": "minus",
        "source": "heroicons",
        "path": "node_modules/heroicons/24/outline/minus.svg"
      },
      "increment": {
        "name": "plus",
        "source": "heroicons",
        "path": "node_modules/heroicons/24/outline/plus.svg"
      }
    }
  },
  "_iconPathMetadata": {
    "description": "Icon paths document where hardcoded/default icons come from (heroicons or custom SVG)",
    "resolutionOrder": [
      "heroicons",
      "custom",
      "unknown"
    ],
    "lastUpdated": "2026-01-26T21:35:36.790Z"
  }
}
